{
  "cities": [
    {
      "city": "Chapel Hill",
      "state": "NC",
      "why": "peace.",
      "id": 1
    },
    {
      "city": "Atlanta",
      "state": "Georgia",
      "why": "ATL hoe",
      "id": 2
    },
    {
      "city": "Durham",
      "state": "North Carolina",
      "why": "Duke University",
      "id": 4
    }
  ],
  "POI": [
    {
      "place": "TOPO",
      "location": "Chapel Hill, NC",
      "why": "shits lit",
      "id": 1
    },
    {
      "place": "The Library",
      "location": "Chapel Hill, NC",
      "why": "shits hype",
      "id": 2
    },
    {
      "place": "Arcana",
      "location": "Durham, NC",
      "why": "Craig plays soul 45s all night",
      "id": 4
    }
  ]
}